setup.py
easy_binomial_gaussian_distributions/Binomialdistribution.py
easy_binomial_gaussian_distributions/Gaussiandistribution.py
easy_binomial_gaussian_distributions/Generaldistribution.py
easy_binomial_gaussian_distributions/__init__.py
easy_binomial_gaussian_distributions.egg-info/PKG-INFO
easy_binomial_gaussian_distributions.egg-info/SOURCES.txt
easy_binomial_gaussian_distributions.egg-info/dependency_links.txt
easy_binomial_gaussian_distributions.egg-info/not-zip-safe
easy_binomial_gaussian_distributions.egg-info/top_level.txt