Metadata-Version: 1.0
Name: easy-binomial-gaussian-distributions
Version: 1.0
Summary: Easy Gaussian and Binomial distributions
Home-page: UNKNOWN
Author: Grant Glass
Author-email: UNKNOWN
License: UNKNOWN
Platform: UNKNOWN
